<?xml version="1.0" encoding="UTF-8"?>
<includes>
    <include file="Window_DialogConfirm.xml" />
    <include file="Window_DialogProgressBar.xml" />

    <include file="Window_DialogGameVideoSelect.xml" />
    <include file="Window_DialogSelect.xml" />

    <include file="Window_DialogPictureInfo.xml" />
    <include file="Window_PictureOSD.xml" />

    <include file="Window_MyMusicNav.xml" />
    <include file="Window_JukeboxMusicNav.xml" />

    <include file="Window_MyPlaylist.xml" />
    <include file="Window_JukeboxPlaylist.xml" />
</includes>
